check_cf_association.py
revealcontrol-1.0.0.dist-info/METADATA
revealcontrol-1.0.0.dist-info/WHEEL
revealcontrol-1.0.0.dist-info/entry_points.txt
revealcontrol-1.0.0.dist-info/top_level.txt
revealcontrol-1.0.0.dist-info/RECORD
