Metadata-Version: 2.1
Name: revealcontrol
Version: 1.0.0
Requires-Dist: requests
